LICENSE.txt
README.md
setup.cfg
setup.py
nomspectra/__init__.py
nomspectra/__main__.py
nomspectra/__version__.py
nomspectra/brutto.py
nomspectra/diff.py
nomspectra/draw.py
nomspectra/gui.py
nomspectra/gui_design.py
nomspectra/gui_dialog.py
nomspectra/metadata.py
nomspectra/recal.py
nomspectra/spectra.py
nomspectra/spectrum.py
nomspectra.egg-info/PKG-INFO
nomspectra.egg-info/SOURCES.txt
nomspectra.egg-info/dependency_links.txt
nomspectra.egg-info/requires.txt
nomspectra.egg-info/top_level.txt