Metadata-Version: 2.1
Name: nomspectra
Version: 0.3.12
Summary: Lib for working with high resolution mass spectra
Home-page: https://github.com/nomspectra/nomspectra
Author: Volikov Alexander, Rukhovich Gleb
Author-email: ab.volikov@gmail.com
License: GPLv3
Platform: UNKNOWN
Classifier: Development Status :: 4 - Beta
Classifier: License :: OSI Approved :: GNU General Public License v3 (GPLv3)
Classifier: Programming Language :: Python :: 3.8
Requires-Python: >=3.8
Provides-Extra: dev
License-File: LICENSE.txt
